flask_paranoid/__init__.py
flask_paranoid/paranoid.py
Flask_Paranoid-0.3.0.dist-info/LICENSE
Flask_Paranoid-0.3.0.dist-info/METADATA
Flask_Paranoid-0.3.0.dist-info/WHEEL
Flask_Paranoid-0.3.0.dist-info/top_level.txt
Flask_Paranoid-0.3.0.dist-info/RECORD
