Metadata-Version: 2.1
Name: Flask-Paranoid
Version: 0.3.0
Summary: Simple user session protection
Home-page: https://github.com/miguelgrinberg/flask-paranoid
Author: Miguel Grinberg
Author-email: miguel.grinberg@gmail.com
License: UNKNOWN
Project-URL: Bug Tracker, https://github.com/miguelgrinberg/flask-paranoid/issues
Platform: UNKNOWN
Classifier: Intended Audience :: Developers
Classifier: Programming Language :: Python :: 3
Classifier: License :: OSI Approved :: MIT License
Classifier: Operating System :: OS Independent
Requires-Python: >=3.6
License-File: LICENSE
